sarwave_config/__init__.py
sarwave_config/e08.yaml
sarwave_config/e09.yaml
sarwave_config/e10.yaml
sarwave_config/e11.yaml
sarwaveifrproc/__init__.py
sarwaveifrproc/l2_wave.py
sarwaveifrproc/main.py
sarwaveifrproc/utils.py
sarwaveifrproc/reference_data/l2-s1b-iw2-wav-dv-20210311t055224-20210311t055250-025963-0318d0-e11.nc
sarwaveifrproc/reference_data/s1a-iw2-slc-dv-20231128t035702-20231128t035727-051412-063451-e01.nc
sarwaveifrproc/reference_data/s1a-iw2-slc-vh-20231128t035702-20231128t035727-051412-063451-002_L1B_xspec_IFR_3.7_nospectra.nc
sarwaveifrproc/reference_data/s1a-iw2-slc-vv-20231128t035702-20231128t035727-051412-063451-005_L1B_xspec_IFR_3.7_nospectra.nc
sarwaveifrproc-2025.9.30.dist-info/licenses/AUTHORS.rst
sarwaveifrproc-2025.9.30.dist-info/licenses/LICENSE
sarwaveifrproc-2025.9.30.dist-info/METADATA
sarwaveifrproc-2025.9.30.dist-info/WHEEL
sarwaveifrproc-2025.9.30.dist-info/entry_points.txt
sarwaveifrproc-2025.9.30.dist-info/top_level.txt
sarwaveifrproc-2025.9.30.dist-info/RECORD
