Metadata-Version: 2.4
Name: sarwaveifrproc
Version: 2025.9.30
Summary: Python library to generate Level-2 WAVE Product starting from Ifremer Level-1B or Level-1C SAR files
Author: Robin Marquart, Antoine Grouazel, Quentin Febvre
License: MIT
Keywords: SAR,wave,reseach,sea-state
Classifier: Programming Language :: Python :: 3
Requires-Python: >=3.9
License-File: LICENSE
License-File: AUTHORS.rst
Requires-Dist: xarray
Requires-Dist: hydra-zen
Requires-Dist: netCDF4
Requires-Dist: pyyaml
Requires-Dist: scipy
Requires-Dist: onnxruntime
Provides-Extra: gpu
Requires-Dist: onnxruntime-gpu; extra == "gpu"
Provides-Extra: joblib
Requires-Dist: hydra-joblib-launcher; extra == "joblib"
Dynamic: license-file
